Metadata-Version: 1.0
Name: tagalog
Version: 0.4.0
Summary: Tagalog: tools for manipulating, tagging and shipping log data
Home-page: https://github.com/nickstenning/tagalog
Author: Nick Stenning
Author-email: nick@whiteink.com
License: MIT
Keywords: sysadmin log logging redis tail
Platform: UNKNOWN
